[
null,
{"id":1,"actions":[{"conditionParam1":0,"conditionParam2":0,"conditionType":0,"rating":5,"skillId":1}],"battlerHue":0,"battlerName":"Bat","dropItems":[{"kind":1,"dataId":6,"denominator":3},{"kind":1,"dataId":10,"denominator":5},{"dataId":1,"denominator":1,"kind":0}],"exp":10,"traits":[{"code":22,"dataId":0,"value":0.95},{"code":22,"dataId":1,"value":0.05},{"code":31,"dataId":1,"value":0}],"gold":40,"name":"Fledermaus","note":"","params":[100,0,30,30,30,30,30,30]},
{"id":2,"actions":[{"conditionParam1":0,"conditionParam2":0,"conditionType":0,"rating":5,"skillId":1}],"battlerHue":0,"battlerName":"Slime","dropItems":[{"kind":1,"dataId":5,"denominator":2},{"kind":1,"dataId":6,"denominator":2},{"dataId":1,"denominator":1,"kind":0}],"exp":20,"traits":[{"code":22,"dataId":0,"value":0.95},{"code":22,"dataId":1,"value":0.05},{"code":31,"dataId":1,"value":0}],"gold":50,"name":"Schleim","note":"","params":[150,0,30,30,30,30,30,30]},
{"id":3,"actions":[{"conditionParam1":0,"conditionParam2":0,"conditionType":0,"rating":5,"skillId":1}],"battlerHue":0,"battlerName":"Orc","dropItems":[{"dataId":1,"denominator":1,"kind":0},{"dataId":1,"denominator":1,"kind":0},{"dataId":1,"denominator":1,"kind":0}],"exp":0,"traits":[{"code":22,"dataId":0,"value":0.95},{"code":22,"dataId":1,"value":0.05},{"code":31,"dataId":1,"value":0}],"gold":0,"name":"Ork","note":"","params":[300,0,30,30,30,30,30,30]},
{"id":4,"actions":[{"conditionParam1":0,"conditionParam2":0,"conditionType":0,"rating":5,"skillId":1}],"battlerHue":0,"battlerName":"Minotaur","dropItems":[{"dataId":1,"denominator":1,"kind":0},{"dataId":1,"denominator":1,"kind":0},{"dataId":1,"denominator":1,"kind":0}],"exp":0,"traits":[{"code":22,"dataId":0,"value":0.95},{"code":22,"dataId":1,"value":0.05},{"code":31,"dataId":1,"value":0}],"gold":0,"name":"Minotaurus","note":"","params":[500,0,30,30,30,30,30,30]},
{"id":5,"actions":[{"conditionParam1":0,"conditionParam2":0,"conditionType":0,"rating":5,"skillId":1}],"battlerHue":101,"battlerName":"Ogre","dropItems":[{"dataId":1,"denominator":1,"kind":0},{"dataId":1,"denominator":1,"kind":0},{"dataId":1,"denominator":1,"kind":0}],"exp":0,"traits":[{"code":22,"dataId":0,"value":0.95},{"code":22,"dataId":1,"value":0.05},{"code":31,"dataId":1,"value":0}],"gold":0,"name":"DUmmy","note":"","params":[300,0,1,10,1,10,10,10]},
{"id":6,"actions":[{"conditionParam1":0,"conditionParam2":0,"conditionType":0,"rating":5,"skillId":1}],"battlerHue":287,"battlerName":"Ghost","dropItems":[{"kind":1,"dataId":7,"denominator":1},{"dataId":1,"denominator":1,"kind":0},{"dataId":1,"denominator":1,"kind":0}],"exp":300,"traits":[{"code":22,"dataId":0,"value":0.95},{"code":22,"dataId":1,"value":0.05},{"code":31,"dataId":1,"value":0}],"gold":400,"name":"Geist der Ruhelosigkeit","note":"","params":[500,0,24,40,24,15,15,15]},
{"id":7,"actions":[{"conditionParam1":0,"conditionParam2":0,"conditionType":0,"rating":5,"skillId":1},{"conditionParam1":2,"conditionParam2":2,"conditionType":1,"rating":9,"skillId":12}],"battlerHue":296,"battlerName":"Vampire","dropItems":[{"kind":1,"dataId":11,"denominator":1},{"kind":1,"dataId":11,"denominator":1},{"kind":1,"dataId":7,"denominator":1}],"exp":500,"traits":[{"code":22,"dataId":0,"value":0.95},{"code":22,"dataId":1,"value":0.05},{"code":31,"dataId":1,"value":0},{"code":22,"dataId":8,"value":0.1}],"gold":600,"name":"M'kure schrecken der Nacht","note":"","params":[1000,100,50,70,40,50,10,10]},
{"id":8,"actions":[{"conditionParam1":0,"conditionParam2":0,"conditionType":0,"rating":5,"skillId":1}],"battlerHue":0,"battlerName":"","dropItems":[{"dataId":1,"denominator":1,"kind":0},{"dataId":1,"denominator":1,"kind":0},{"dataId":1,"denominator":1,"kind":0}],"exp":0,"traits":[{"code":22,"dataId":0,"value":0.95},{"code":22,"dataId":1,"value":0.05},{"code":31,"dataId":1,"value":0}],"gold":0,"name":"","note":"","params":[1000,0,30,10,10,10,10,10]},
{"id":9,"actions":[{"conditionParam1":0,"conditionParam2":0,"conditionType":0,"rating":5,"skillId":1}],"battlerHue":0,"battlerName":"","dropItems":[{"dataId":1,"denominator":1,"kind":0},{"dataId":1,"denominator":1,"kind":0},{"dataId":1,"denominator":1,"kind":0}],"exp":0,"traits":[{"code":22,"dataId":0,"value":0.95},{"code":22,"dataId":1,"value":0.05},{"code":31,"dataId":1,"value":0}],"gold":0,"name":"","note":"","params":[100,0,10,10,10,10,10,10]},
{"id":10,"actions":[{"conditionParam1":0,"conditionParam2":0,"conditionType":0,"rating":5,"skillId":1}],"battlerHue":0,"battlerName":"","dropItems":[{"dataId":1,"denominator":1,"kind":0},{"dataId":1,"denominator":1,"kind":0},{"dataId":1,"denominator":1,"kind":0}],"exp":0,"traits":[{"code":22,"dataId":0,"value":0.95},{"code":22,"dataId":1,"value":0.05},{"code":31,"dataId":1,"value":0}],"gold":0,"name":"","note":"","params":[100,0,10,10,10,10,10,10]},
{"id":11,"actions":[{"conditionParam1":0,"conditionParam2":0,"conditionType":0,"rating":5,"skillId":1}],"battlerHue":0,"battlerName":"","dropItems":[{"dataId":1,"denominator":1,"kind":0},{"dataId":1,"denominator":1,"kind":0},{"dataId":1,"denominator":1,"kind":0}],"exp":0,"traits":[{"code":22,"dataId":0,"value":0.95},{"code":22,"dataId":1,"value":0.05},{"code":31,"dataId":1,"value":0}],"gold":0,"name":"","note":"","params":[100,0,10,10,10,10,10,10]},
{"id":12,"actions":[{"conditionParam1":0,"conditionParam2":0,"conditionType":0,"rating":5,"skillId":1}],"battlerHue":0,"battlerName":"","dropItems":[{"dataId":1,"denominator":1,"kind":0},{"dataId":1,"denominator":1,"kind":0},{"dataId":1,"denominator":1,"kind":0}],"exp":0,"traits":[{"code":22,"dataId":0,"value":0.95},{"code":22,"dataId":1,"value":0.05},{"code":31,"dataId":1,"value":0}],"gold":0,"name":"","note":"","params":[100,0,10,10,10,10,10,10]},
{"id":13,"actions":[{"conditionParam1":0,"conditionParam2":0,"conditionType":0,"rating":5,"skillId":1}],"battlerHue":0,"battlerName":"","dropItems":[{"dataId":1,"denominator":1,"kind":0},{"dataId":1,"denominator":1,"kind":0},{"dataId":1,"denominator":1,"kind":0}],"exp":0,"traits":[{"code":22,"dataId":0,"value":0.95},{"code":22,"dataId":1,"value":0.05},{"code":31,"dataId":1,"value":0}],"gold":0,"name":"","note":"","params":[100,0,10,10,10,10,10,10]},
{"id":14,"actions":[{"conditionParam1":0,"conditionParam2":0,"conditionType":0,"rating":5,"skillId":1}],"battlerHue":0,"battlerName":"","dropItems":[{"dataId":1,"denominator":1,"kind":0},{"dataId":1,"denominator":1,"kind":0},{"dataId":1,"denominator":1,"kind":0}],"exp":0,"traits":[{"code":22,"dataId":0,"value":0.95},{"code":22,"dataId":1,"value":0.05},{"code":31,"dataId":1,"value":0}],"gold":0,"name":"","note":"","params":[100,0,10,10,10,10,10,10]},
{"id":15,"actions":[{"conditionParam1":0,"conditionParam2":0,"conditionType":0,"rating":5,"skillId":1}],"battlerHue":0,"battlerName":"","dropItems":[{"dataId":1,"denominator":1,"kind":0},{"dataId":1,"denominator":1,"kind":0},{"dataId":1,"denominator":1,"kind":0}],"exp":0,"traits":[{"code":22,"dataId":0,"value":0.95},{"code":22,"dataId":1,"value":0.05},{"code":31,"dataId":1,"value":0}],"gold":0,"name":"","note":"","params":[100,0,10,10,10,10,10,10]},
{"id":16,"actions":[{"conditionParam1":0,"conditionParam2":0,"conditionType":0,"rating":5,"skillId":1}],"battlerHue":0,"battlerName":"","dropItems":[{"dataId":1,"denominator":1,"kind":0},{"dataId":1,"denominator":1,"kind":0},{"dataId":1,"denominator":1,"kind":0}],"exp":0,"traits":[{"code":22,"dataId":0,"value":0.95},{"code":22,"dataId":1,"value":0.05},{"code":31,"dataId":1,"value":0}],"gold":0,"name":"","note":"","params":[100,0,10,10,10,10,10,10]},
{"id":17,"actions":[{"conditionParam1":0,"conditionParam2":0,"conditionType":0,"rating":5,"skillId":1}],"battlerHue":0,"battlerName":"","dropItems":[{"dataId":1,"denominator":1,"kind":0},{"dataId":1,"denominator":1,"kind":0},{"dataId":1,"denominator":1,"kind":0}],"exp":0,"traits":[{"code":22,"dataId":0,"value":0.95},{"code":22,"dataId":1,"value":0.05},{"code":31,"dataId":1,"value":0}],"gold":0,"name":"","note":"","params":[100,0,10,10,10,10,10,10]},
{"id":18,"actions":[{"conditionParam1":0,"conditionParam2":0,"conditionType":0,"rating":5,"skillId":1}],"battlerHue":0,"battlerName":"","dropItems":[{"dataId":1,"denominator":1,"kind":0},{"dataId":1,"denominator":1,"kind":0},{"dataId":1,"denominator":1,"kind":0}],"exp":0,"traits":[{"code":22,"dataId":0,"value":0.95},{"code":22,"dataId":1,"value":0.05},{"code":31,"dataId":1,"value":0}],"gold":0,"name":"","note":"","params":[100,0,10,10,10,10,10,10]},
{"id":19,"actions":[{"conditionParam1":0,"conditionParam2":0,"conditionType":0,"rating":5,"skillId":1}],"battlerHue":0,"battlerName":"","dropItems":[{"dataId":1,"denominator":1,"kind":0},{"dataId":1,"denominator":1,"kind":0},{"dataId":1,"denominator":1,"kind":0}],"exp":0,"traits":[{"code":22,"dataId":0,"value":0.95},{"code":22,"dataId":1,"value":0.05},{"code":31,"dataId":1,"value":0}],"gold":0,"name":"","note":"","params":[100,0,10,10,10,10,10,10]},
{"id":20,"actions":[{"conditionParam1":0,"conditionParam2":0,"conditionType":0,"rating":5,"skillId":1}],"battlerHue":0,"battlerName":"","dropItems":[{"dataId":1,"denominator":1,"kind":0},{"dataId":1,"denominator":1,"kind":0},{"dataId":1,"denominator":1,"kind":0}],"exp":0,"traits":[{"code":22,"dataId":0,"value":0.95},{"code":22,"dataId":1,"value":0.05},{"code":31,"dataId":1,"value":0}],"gold":0,"name":"","note":"","params":[100,0,10,10,10,10,10,10]}
]